MeowthLogger/__init__.py
MeowthLogger/constants.py
MeowthLogger/errors.py
MeowthLogger/app/__init__.py
MeowthLogger/app/logger.py
MeowthLogger/app/settings.py
MeowthLogger/app/config/__init__.py
MeowthLogger/app/config/abstract.py
MeowthLogger/app/config/config.py
MeowthLogger/app/config/console.py
MeowthLogger/app/config/file.py
MeowthLogger/app/config/stream.py
MeowthLogger/app/config/utils.py
MeowthLogger/app/config/uvicorn.py
MeowthLogger/app/parser/__init__.py
MeowthLogger/app/parser/files.py
MeowthLogger/app/parser/parser.py
MeowthLogger/formatters/__init__.py
MeowthLogger/formatters/colorised.py
MeowthLogger/formatters/default.py
MeowthLogger/formatters/formatter.py
MeowthLogger/handlers/__init__.py
MeowthLogger/handlers/file_handler.py
MeowthLogger/utilities/abstractions.py
MeowthLogger/utilities/custom_hour.py
MeowthLogger/utilities/dates.py
MeowthLogger/utilities/fastapi/log_stream.py
MeowthLogger/utilities/fastapi/views.py
MeowthLogger/utilities/log_streaming/log_streaming.py
MeowthLogger/utilities/log_streaming/stream_manager.py
meowthlogger-2.5.2.dist-info/licenses/LICENSE
meowthlogger-2.5.2.dist-info/METADATA
meowthlogger-2.5.2.dist-info/WHEEL
meowthlogger-2.5.2.dist-info/top_level.txt
meowthlogger-2.5.2.dist-info/RECORD
