Metadata-Version: 2.4
Name: MeowthLogger
Version: 2.5.2
Summary: Colorised logger for python, using logging python lib
Author-email: Meowthpxnk <meowthpxnk@gmail.com>
License: MIT
Project-URL: github, https://github.com/meowthpxnk/MeowthLogger
Classifier: Programming Language :: Python :: 3
Classifier: License :: OSI Approved :: MIT License
Classifier: Operating System :: OS Independent
Requires-Python: >=3.7
License-File: LICENSE
Requires-Dist: colorama==0.4.6
Dynamic: license-file
